Verilog Basics/Combinational Circuits - Gate Level/Data Selection and Routing Circuits/MUX/4x1 MUX using 2x1 MUX/mux_2x1.v
module mux_2x1 (
    output y,
    input a, b, s
);
    wire sn, i, j;
    not G1(sn, s);
    and G2(i, a, sn);
    and G3(j, b, s);
    or G4(y, i, j);


endmodule

Verilog Basics/Combinational Circuits - Gate Level/Data Selection and Routing Circuits/MUX/2x1 MUX/tb_mux_2x1.v
`timescale 1ns/1ps

module tb_mux_2x1;
    reg a, b, s;
    wire y;

    mux_2x1 DUT(y, a, b, s);

    initial begin
        $dumpfile("mux_2x1.vcd");
        $dumpvars(0, tb_mux_2x1);
        $display("Time\tA B S | Y");
        $monitor("%g\t%b %b %b | %b", $time, a, b, s, y);

        // Test all 8 input combinations
        a = 0; b = 0; s = 0; #10;
        a = 0; b = 1; s = 0; #10;
        a = 1; b = 0; s = 0; #10;
        a = 1; b = 1; s = 0; #10;
        a = 0; b = 0; s = 1; #10;
        a = 0; b = 1; s = 1; #10;
        a = 1; b = 0; s = 1; #10;
        a = 1; b = 1; s = 1; #10;

        $finish;
    end
endmodule

Verilog Basics/Combinational Circuits - Gate Level/Data Selection and Routing Circuits/MUX/2x1 MUX/mux_2x1.vcd
$date
	Sat Jun 14 20:14:52 2025
$end
$version
	Icarus Verilog
$end
$timescale
	1ps
$end
$scope module tb_mux_2x1 $end
$var wire 1 ! y $end
$var reg 1 " a $end
$var reg 1 # b $end
$var reg 1 $ s $end
$scope module DUT $end
$var wire 1 " a $end
$var wire 1 # b $end
$var wire 1 % i $end
$var wire 1 & j $end
$var wire 1 $ s $end
$var wire 1 ' sn $end
$var wire 1 ! y $end
$upscope $end
$upscope $end
$enddefinitions $end
$comment Show the parameter values. $end
$dumpall
$end
#0
$dumpvars
1'
0&
0%
0$
0#
0"
0!
$end
#10000
1#
#20000
1!
1%
0#
1"
#30000
1#
#40000
0!
0'
0%
1$
0#
0"
#50000
1!
1&
1#
#60000
0!
0&
0#
1"
#70000
1!
1&
1#
