Verilog Basics/Combinational Circuits - Gate Level/Arithmetic Circuits/Full Adder using Half Adder/ha.v
module half_adder (
    output sum, carry,
    input a, b
);
    xor(sum, a, b);
    and(carry, a, b);
endmodule

Verilog Basics/Combinational Circuits - Gate Level/Arithmetic Circuits/Full Adder using Half Adder/top.v
`include "ha.v"

module full_adder (
    output sum, carry,
    input a, b, c
);
    wire i, j, k;

    half_adder HA1(i, j, a, b);
    half_adder HA2(sum, k, i, c);
    or(carry, j, k);
endmodule

Verilog Basics/Combinational Circuits - Gate Level/Arithmetic Circuits/Full Adder using Half Adder/tb_fa.v
`timescale 1ns/1ps

module tb_full_adder;

    reg A, B, C;
    wire SUM, CARRY;

    full_adder uut (.sum(SUM), .carry(CARRY), .a(A), .b(B), .c(C));

    initial begin
        A = 0;
        B = 0;
        C = 0;
    end

    always #5 A = ~A;

    always #11 B = ~B;

    always #8 C = ~C;

    initial begin
        $dumpfile("full_adder.vcd");  
        $dumpvars(0, tb_full_adder);  

        #50 $finish;
    end

    initial begin
        $monitor("Time = %0t ns: A=%b, B=%b, C=%b → SUM=%b, CARRY=%b", $time, A, B, C, SUM, CARRY);
    end

endmodule

Verilog Basics/Combinational Circuits - Gate Level/Arithmetic Circuits/Full Adder using logic gates/full_adder.vcd
$date
	Thu Jun 12 14:40:04 2025
$end
$version
	Icarus Verilog
$end
$timescale
	1ps
$end
$scope module tb_full_adder $end
$var wire 1 ! SUM $end
$var wire 1 " CARRY $end
$var reg 1 # A $end
$var reg 1 $ B $end
$var reg 1 % C $end
$scope module uut $end
$var wire 1 # a $end
$var wire 1 $ b $end
$var wire 1 % c $end
$var wire 1 " carry $end
$var wire 1 & i $end
$var wire 1 ' j $end
$var wire 1 ( k $end
$var wire 1 ! sum $end
$upscope $end
$upscope $end
$enddefinitions $end
$comment Show the parameter values. $end
$dumpall
$end
#0
$dumpvars
0(
0'
0&
0%
0$
0#
0"
0!
$end
#5000
1!
1&
1#
#8000
1"
0!
1(
1%
#10000
0"
1!
0(
0&
0#
#11000
1"
0!
1(
1&
1$
#15000
1!
0(
0&
1'
1#
#16000
0!
0%
#20000
1!
0"
1&
0'
0#
#22000
0!
0&
0$
#24000
1!
1%
#25000
1"
0!
1(
1&
1#
#30000
0"
1!
0(
0&
0#
#32000
0!
0%
#33000
1!
1&
1$
#35000
0!
1"
0&
1'
1#
#40000
1(
1"
1&
0'
0!
0#
1%
#44000
0"
1!
0(
0&
0$
#45000
1"
0!
1(
1&
1#
#48000
0"
1!
0(
0%
#50000
0!
0&
0#
