Verilog Basics/Combinational Circuits - Gate Level/Arithmetic Circuits/Full Adder using Half Adder/ha.v
module half_adder (
    output sum, carry,
    input a, b
);
    xor(sum, a, b);
    and(carry, a, b);
endmodule

Verilog Basics/Combinational Circuits - Gate Level/Arithmetic Circuits/Half Adder/tb_ha.v
`timescale 1ns/1ps

module tb_half_adder;

    reg A, B;
    wire SUM, CARRY;

    half_adder uut (.sum(SUM), .carry(CARRY), .a(A), .b(B));

    initial begin
        A = 0;
        B = 0;
    end

    always #7 A = ~A;

    always #11 B = ~B;

    initial begin
        $dumpfile("half_adder.vcd");  
        $dumpvars(0, tb_half_adder);  

        #50 $finish;
    end

    initial begin
        $monitor("Time = %0t ns: A=%b, B=%b → SUM=%b, CARRY=%b", $time, A, B, SUM, CARRY);
    end

endmodule

Verilog Basics/Combinational Circuits - Gate Level/Arithmetic Circuits/Half Adder/half_adder.vcd
$date
	Thu Jun 12 14:26:08 2025
$end
$version
	Icarus Verilog
$end
$timescale
	1ps
$end
$scope module tb_half_adder $end
$var wire 1 ! SUM $end
$var wire 1 " CARRY $end
$var reg 1 # A $end
$var reg 1 $ B $end
$scope module uut $end
$var wire 1 # a $end
$var wire 1 $ b $end
$var wire 1 " carry $end
$var wire 1 ! sum $end
$upscope $end
$upscope $end
$enddefinitions $end
$comment Show the parameter values. $end
$dumpall
$end
#0
$dumpvars
0$
0#
0"
0!
$end
#7000
1!
1#
#11000
0!
1"
1$
#14000
1!
0"
0#
#21000
0!
1"
1#
#22000
1!
0"
0$
#28000
0!
0#
#33000
1!
1$
#35000
0!
1"
1#
#42000
1!
0"
0#
#44000
0!
0$
#49000
1!
1#
