Verilog Basics/Combinational Circuits - Gate Level/Arithmetic Circuits/Half Subtractor using NAND gates/top.v
module half_sub (
    output diff, borr,
    input a, b
);
    wire i, j, k;
    nand N1(i, a, b);
    nand N2(j, a, i);
    nand N3(k, b, i);
    nand N4(diff, j, k);
    nand N5(borr, k, k);

endmodule

Verilog Basics/Combinational Circuits - Gate Level/Arithmetic Circuits/Full Subtractor using Half Subtractor/top.v
`include "hs.v"

module full_sub (
    output diff, borr,
    input a, b, c
);
    wire i, j, k;
    half_sub HS1(i, j, a, b);
    half_sub HS2(diff, k, i, c);
    or(borr, k, j);
    
endmodule

Verilog Basics/Combinational Circuits - Gate Level/Arithmetic Circuits/Full Subtractor using Half Subtractor/tb_fs.v
`timescale 1ns/1ps

module tb_full_sub;

    reg A, B, C;
    wire DIFF, BORR;

    full_sub uut (.diff(DIFF), .borr(BORR), .a(A), .b(B), .c(C));

    initial begin
        A = 0;
        B = 0;
        C = 0;
    end

    always #5 A = ~A;

    always #11 B = ~B;

    always #8 C = ~C;

    initial begin
        $dumpfile("full_sub.vcd");  
        $dumpvars(0, tb_full_sub);  

        #50 $finish;
    end

    initial begin
        $monitor("Time = %0t ns: A=%b, B=%b, C=%b → DIFF=%b, BORR=%b", $time, A, B, C, DIFF, BORR);
    end

endmodule

Verilog Basics/Combinational Circuits - Gate Level/Arithmetic Circuits/Full Subtractor using Half Subtractor/full_sub.vcd
$date
	Thu Jun 12 18:07:55 2025
$end
$version
	Icarus Verilog
$end
$timescale
	1ps
$end
$scope module tb_full_sub $end
$var wire 1 ! DIFF $end
$var wire 1 " BORR $end
$var reg 1 # A $end
$var reg 1 $ B $end
$var reg 1 % C $end
$scope module uut $end
$var wire 1 # a $end
$var wire 1 $ b $end
$var wire 1 " borr $end
$var wire 1 % c $end
$var wire 1 & k $end
$var wire 1 ' j $end
$var wire 1 ( i $end
$var wire 1 ! diff $end
$scope module HS1 $end
$var wire 1 # a $end
$var wire 1 $ b $end
$var wire 1 ' borr $end
$var wire 1 ( diff $end
$var wire 1 ) i $end
$var wire 1 * j $end
$var wire 1 + k $end
$upscope $end
$scope module HS2 $end
$var wire 1 ( a $end
$var wire 1 % b $end
$var wire 1 & borr $end
$var wire 1 ! diff $end
$var wire 1 , i $end
$var wire 1 - j $end
$var wire 1 . k $end
$upscope $end
$upscope $end
$upscope $end
$enddefinitions $end
$comment Show the parameter values. $end
$dumpall
$end
#0
$dumpvars
1.
1-
1,
1+
1*
1)
0(
0'
0&
0%
0$
0#
0"
0!
$end
#5000
1!
0-
1(
0*
1#
#8000
0!
0"
1-
0&
0,
1.
1%
#10000
1"
1!
1&
0.
1,
0(
1*
0#
#11000
0!
0&
1.
0,
1-
1(
1'
0+
1$
#15000
1!
1&
0.
1,
1"
0(
0'
1+
0)
1*
1#
#16000
0"
0!
0&
1.
0%
#20000
1!
0-
1"
1(
1'
0+
1)
0#
#22000
0!
1-
0"
0(
0'
1+
0$
#24000
1"
1!
1&
0.
1%
#25000
0"
0!
0&
1.
0,
1-
1(
0*
1#
#30000
1"
1!
1&
0.
1,
0(
1*
0#
#32000
0"
0!
0&
1.
0%
#33000
1!
0-
1"
1(
1'
0+
1$
#35000
0!
1-
0"
0(
0'
1+
0)
1*
1#
#40000
0,
1-
1(
1'
1"
0+
0!
0&
1)
1.
0#
1%
#44000
1!
1&
0.
1,
1"
0(
0'
1+
0$
#45000
0"
0!
0&
1.
0,
1-
1(
0*
1#
#48000
1!
0-
1,
0%
#50000
0!
1-
0(
1*
0#
