Verilog Basics/Combinational Circuits - Gate Level/Data Selection and Routing Circuits/Encoders/8x3 Encoder/top.v
module enc_8x3 (
    output [2:0] y,
    input [7:0] d
);
    or G1(y[0], d[1], d[3], d[5], d[7]);
    or G2(y[1], d[2], d[3], d[6], d[7]);
    or G3(y[2], d[4], d[5], d[6], d[7]);

endmodule

Verilog Basics/Combinational Circuits - Gate Level/Data Selection and Routing Circuits/Encoders/8x3 Encoder/tb_enc_8x3.v
`timescale 1ns/1ps

module tb_enc_8x3;

    reg [7:0] d;
    wire [2:0] y;

    enc_8x3 E1(y, d);

    initial begin
        $dumpfile("enc_8x3.vcd");
        $dumpvars(0, tb_enc_8x3);

        $display("Time\t\tD\t\t|\tY");
        $display("---------------------------------------");

        d = 8'b00000001; #10;  // d0
        $display("%0t\t%b\t|\t%b", $time, d, y);

        d = 8'b00000010; #10;  // d1
        $display("%0t\t%b\t|\t%b", $time, d, y);

        d = 8'b00000100; #10;  // d2
        $display("%0t\t%b\t|\t%b", $time, d, y);

        d = 8'b00001000; #10;  // d3
        $display("%0t\t%b\t|\t%b", $time, d, y);

        d = 8'b00010000; #10;  // d4
        $display("%0t\t%b\t|\t%b", $time, d, y);

        d = 8'b00100000; #10;  // d5
        $display("%0t\t%b\t|\t%b", $time, d, y);

        d = 8'b01000000; #10;  // d6
        $display("%0t\t%b\t|\t%b", $time, d, y);

        d = 8'b10000000; #10;  // d7
        $display("%0t\t%b\t|\t%b", $time, d, y);

        // Multiple input high (non-priority encoder behavior)
        d = 8'b00001100; #10;  // d2 and d3
        $display("%0t\t%b\t|\t%b", $time, d, y);

        d = 8'b11111111; #10;  // all high
        $display("%0t\t%b\t|\t%b", $time, d, y);

        $finish;
    end

endmodule

Verilog Basics/Combinational Circuits - Gate Level/Data Selection and Routing Circuits/Encoders/8x3 Encoder/enc_8x3.vcd
$date
	Sun Jun 15 15:32:08 2025
$end
$version
	Icarus Verilog
$end
$timescale
	1ps
$end
$scope module tb_enc_8x3 $end
$var wire 3 ! y [2:0] $end
$var reg 8 " d [7:0] $end
$scope module E1 $end
$var wire 8 # d [7:0] $end
$var wire 3 $ y [2:0] $end
$upscope $end
$upscope $end
$enddefinitions $end
$comment Show the parameter values. $end
$dumpall
$end
#0
$dumpvars
b0 $
b1 #
b1 "
b0 !
$end
#10000
b1 !
b1 $
b10 "
b10 #
#20000
b10 !
b10 $
b100 "
b100 #
#30000
b11 !
b11 $
b1000 "
b1000 #
#40000
b100 !
b100 $
b10000 "
b10000 #
#50000
b101 !
b101 $
b100000 "
b100000 #
#60000
b110 !
b110 $
b1000000 "
b1000000 #
#70000
b111 !
b111 $
b10000000 "
b10000000 #
#80000
b11 !
b11 $
b1100 "
b1100 #
#90000
b111 !
b111 $
b11111111 "
b11111111 #
