Verilog Basics/Combinational Circuits - Gate Level/Arithmetic Circuits/Half Subtractor using NAND gates/top.v
module half_sub (
    output diff, borr,
    input a, b
);
    wire i, j, k;
    nand N1(i, a, b);
    nand N2(j, a, i);
    nand N3(k, b, i);
    nand N4(diff, j, k);
    nand N5(borr, k, k);

endmodule

Verilog Basics/Combinational Circuits - Gate Level/Arithmetic Circuits/Half Subtractor using NAND gates/tb_hs.v
`timescale 1ns/1ps

module tb_half_sub;

    reg A, B;
    wire DIFF, BORR;

    half_sub uut (.diff(DIFF), .borr(BORR), .a(A), .b(B));

    initial begin
        A = 0;
        B = 0;
    end

    always #7 A = ~A;

    always #11 B = ~B;

    initial begin
        $dumpfile("half_sub.vcd");  
        $dumpvars(0, tb_half_sub);  

        #50 $finish;
    end

    initial begin
        $monitor("Time = %0t ns: A=%b, B=%b → DIFF=%b, BORR=%b", $time, A, B, DIFF, BORR);
    end

endmodule

Verilog Basics/Combinational Circuits - Gate Level/Arithmetic Circuits/Half Subtractor using NAND gates/half_sub.vcd
$date
	Thu Jun 12 17:08:21 2025
$end
$version
	Icarus Verilog
$end
$timescale
	1ps
$end
$scope module tb_half_sub $end
$var wire 1 ! DIFF $end
$var wire 1 " BORR $end
$var reg 1 # A $end
$var reg 1 $ B $end
$scope module uut $end
$var wire 1 # a $end
$var wire 1 $ b $end
$var wire 1 " borr $end
$var wire 1 ! diff $end
$var wire 1 % i $end
$var wire 1 & j $end
$var wire 1 ' k $end
$upscope $end
$upscope $end
$enddefinitions $end
$comment Show the parameter values. $end
$dumpall
$end
#0
$dumpvars
1'
1&
1%
0$
0#
0"
0!
$end
#7000
1!
0&
1#
#11000
0!
1&
0"
0%
1'
1$
#14000
1!
1"
0'
1%
0#
#21000
0!
0"
1'
0%
1&
1#
#22000
1!
0&
1%
0$
#28000
0!
1&
0#
#33000
1!
1"
0'
1$
#35000
0!
0"
1'
0%
1&
1#
#42000
1!
1"
0'
1%
0#
#44000
0!
0"
1'
0$
#49000
1!
0&
1#
