Verilog Basics/Basic Gates - Switch Level/XOR/inv.v
module inverter (
    input a,
    output b
);
    // power
    supply1 vdd;
    supply0 gnd;
    
    // pull up network
    pmos Q1(b, vdd, a);

    // pull down network
    nmos Q2(b, gnd, a);
endmodule

Verilog Basics/Basic Gates - Switch Level/XOR/top.v
`include "inv.v"

module XOR (
    output c,
    input a, b
);
    wire i, j, l, m, n;
    
    // power
    supply1 vdd;
    supply0 gnd;

    // inverting inputs
    inverter inv_net1(.a(a), .b(i));
    inverter inv_net2(.a(b), .b(j));

    // pull up network
    pmos Q1(l, vdd, a);
    pmos Q2(l, vdd, b);
    pmos Q3(c, l, i);
    pmos Q4(c, l, j);

    // pull down network
    nmos Q5(c, m, a);
    nmos Q6(m, gnd, b);
    nmos Q7(c, n, i);
    nmos Q8(n, gnd, j);

endmodule

Verilog Basics/Basic Gates - Switch Level/XOR/tb_xor.v
`timescale 1ns / 1ps

module tb_xor;
    reg A, B;          
    wire Y;           

    XOR uut (.a(A), .b(B), .c(Y));

    initial begin
        A = 0;
        B = 0;
    end

    always #7 A = ~A;

    always #11 B = ~B;

    initial begin
        $dumpfile("xor.vcd");  
        $dumpvars(0, tb_xor);  

        #50 $finish;
    end

    initial begin
        $monitor("Time = %0t ns: A=%b, B=%b → Y=%b", $time, A, B, Y);
    end
endmodule

Verilog Basics/Basic Gates - Switch Level/XOR/xor.vcd
$date
	Wed Jun 11 18:26:41 2025
$end
$version
	Icarus Verilog
$end
$timescale
	1ps
$end
$scope module tb_xor $end
$var wire 1 ! Y $end
$var reg 1 " A $end
$var reg 1 # B $end
$scope module uut $end
$var wire 1 " a $end
$var wire 1 # b $end
$var wire 1 ! c $end
$var wire 1 $ gnd $end
$var wire 1 % i $end
$var wire 1 & j $end
$var wire 1 ' l $end
$var wire 1 ( m $end
$var wire 1 ) n $end
$var wire 1 * vdd $end
$scope module inv_net1 $end
$var wire 1 " a $end
$var wire 1 % b $end
$var wire 1 + gnd $end
$var wire 1 , vdd $end
$upscope $end
$scope module inv_net2 $end
$var wire 1 # a $end
$var wire 1 & b $end
$var wire 1 - gnd $end
$var wire 1 . vdd $end
$upscope $end
$upscope $end
$upscope $end
$enddefinitions $end
$comment Show the parameter values. $end
$dumpall
$end
#0
$dumpvars
1.
0-
1,
0+
1*
0)
z(
1'
1&
1%
0$
0#
0"
0!
$end
#7000
1!
0%
1"
#11000
z'
0!
0(
z)
0&
1#
#14000
1'
1!
1%
0"
#21000
z'
0!
0%
1"
#22000
1'
1!
z(
0)
1&
0#
#28000
0!
1%
0"
#33000
0(
1!
z)
0&
1#
#35000
z'
0!
0%
1"
#42000
1'
1!
1%
0"
#44000
z(
0!
0)
1&
0#
#49000
1!
0%
1"
