Verilog Basics/Basic Gates - Switch Level/NOR/top.v
module NOR (
    output c,
    input a,b
);
    wire x;
    
    // power
    supply1 vdd;
    supply0 gnd;

    // pull up network
    pmos Q1(x, vdd, a);
    pmos Q2(c, x, b);

    // pull down network
    nmos Q3(c, gnd, a);
    nmos Q4(c, gnd, b);
    
endmodule

Verilog Basics/Basic Gates - Switch Level/NOR/tb_nor.v
`timescale 1ns / 1ps

module tb_nor;
    reg A, B;          
    wire Y;           

    NOR uut (.a(A), .b(B), .c(Y));

    initial begin
        A = 0;
        B = 0;
    end

    always #7 A = ~A;

    always #11 B = ~B;

    initial begin
        $dumpfile("nor.vcd");  
        $dumpvars(0, tb_nor);  

        #50 $finish;
    end

    initial begin
        $monitor("Time = %0t ns: A=%b, B=%b → Y=%b", $time, A, B, Y);
    end
endmodule

Verilog Basics/Basic Gates - Switch Level/NOR/nor.vcd
$date
	Wed Jun 11 16:42:20 2025
$end
$version
	Icarus Verilog
$end
$timescale
	1ps
$end
$scope module tb_nor $end
$var wire 1 ! Y $end
$var reg 1 " A $end
$var reg 1 # B $end
$scope module uut $end
$var wire 1 " a $end
$var wire 1 # b $end
$var wire 1 ! c $end
$var wire 1 $ gnd $end
$var wire 1 % vdd $end
$var wire 1 & x $end
$upscope $end
$upscope $end
$enddefinitions $end
$comment Show the parameter values. $end
$dumpall
$end
#0
$dumpvars
1&
1%
0$
0#
0"
1!
$end
#7000
z&
0!
1"
#11000
1#
#14000
1&
0"
#21000
z&
1"
#22000
0#
#28000
1&
1!
0"
#33000
0!
1#
#35000
z&
1"
#42000
1&
0"
#44000
1!
0#
#49000
z&
0!
1"
