Verilog Basics/Combinational Circuits - Gate Level/Data Selection and Routing Circuits/Priority Encoder/top.v
module p_enc (
    output [1:0] y,
    output v,
    input [3:0] d
);
    wire d2_n, i;
    not N1(d2_n, d[2]);
    or O1(y[1], d[3], d[2]);
    and A1(i, d2_n, d[1]);
    or O2(y[0], d[3], i);
    or O3(v, d[3], d[2], d[1], d[0]);

endmodule

Verilog Basics/Combinational Circuits - Gate Level/Data Selection and Routing Circuits/Priority Encoder/tb_p_enc.v
`timescale 1ns/1ps

module tb_p_enc;

    reg [3:0] d;
    wire [1:0] y;
    wire v;

    p_enc uut(y, v, d);

    initial begin
        $dumpfile("p_enc.vcd");
        $dumpvars(0, tb_p_enc);

        $display("Time\tInput\t|\tOutput y\tValid v");
        $display("---------------------------------------------");

        d = 4'b0000; #10;
        $display("%0t\t%b\t|\t%2b\t\t%b", $time, d, y, v);

        d = 4'b0001; #10;
        $display("%0t\t%b\t|\t%2b\t\t%b", $time, d, y, v);

        d = 4'b0010; #10;
        $display("%0t\t%b\t|\t%2b\t\t%b", $time, d, y, v);

        d = 4'b0100; #10;
        $display("%0t\t%b\t|\t%2b\t\t%b", $time, d, y, v);

        d = 4'b1000; #10;
        $display("%0t\t%b\t|\t%2b\t\t%b", $time, d, y, v);

        d = 4'b0011; #10; // d1 has priority over d0
        $display("%0t\t%b\t|\t%2b\t\t%b", $time, d, y, v);

        d = 4'b0110; #10; // d2 has priority over d1
        $display("%0t\t%b\t|\t%2b\t\t%b", $time, d, y, v);

        d = 4'b1111; #10; // d3 has highest priority
        $display("%0t\t%b\t|\t%2b\t\t%b", $time, d, y, v);

        $finish;
    end

endmodule

Verilog Basics/Combinational Circuits - Gate Level/Data Selection and Routing Circuits/Priority Encoder/p_enc.vcd
$date
	Sun Jun 15 17:11:15 2025
$end
$version
	Icarus Verilog
$end
$timescale
	1ps
$end
$scope module tb_p_enc $end
$var wire 2 ! y [1:0] $end
$var wire 1 " v $end
$var reg 4 # d [3:0] $end
$scope module uut $end
$var wire 4 $ d [3:0] $end
$var wire 1 % d2_n $end
$var wire 1 & i $end
$var wire 1 " v $end
$var wire 2 ' y [1:0] $end
$upscope $end
$upscope $end
$enddefinitions $end
$comment Show the parameter values. $end
$dumpall
$end
#0
$dumpvars
b0 '
0&
1%
b0 $
b0 #
0"
b0 !
$end
#10000
1"
b1 #
b1 $
#20000
b1 !
b1 '
1&
b10 #
b10 $
#30000
0%
b10 !
b10 '
0&
b100 #
b100 $
#40000
1%
b11 !
b11 '
b1000 #
b1000 $
#50000
1&
b1 !
b1 '
b11 #
b11 $
#60000
0&
0%
b10 !
b10 '
b110 #
b110 $
#70000
b11 !
b11 '
b1111 #
b1111 $
