Verilog Basics/Combinational Circuits - Gate Level/Data Selection and Routing Circuits/DEMUX/1x4 DEMUX using 1x2 DEMUX/demux_1x2.v
module demux_1x2 (
    output [1:0] y,
    input a, s
);
    wire sn;
    not G1(sn, s);
    and G2(y[0], a, sn);
    and G3(y[1], a, s);

endmodule

Verilog Basics/Combinational Circuits - Gate Level/Data Selection and Routing Circuits/DEMUX/1x4 DEMUX using 1x2 DEMUX/top.v
`include "demux_1x2.v"

module demux_1x4 (
    output [3:0] y,
    input a,
    input [1:0] s
);
    wire [1:0] i;
    demux_1x2 D1(i, a, s[1]);
    demux_1x2 D2(y[1:0], i[0], s[0]);
    demux_1x2 D3(y[3:2], i[1], s[0]);
    
endmodule

Verilog Basics/Combinational Circuits - Gate Level/Data Selection and Routing Circuits/DEMUX/1x4 DEMUX using 1x2 DEMUX/tb_demux_1x4.v
`timescale 1ns/1ps

module tb_demux_1x4;
    reg a;
    reg [1:0] s;
    wire [3:0] y;

    demux_1x4 DUT(y, a, s);

    initial begin
        $dumpfile("demux_1x4.vcd");
        $dumpvars(0, tb_demux_1x4);
        $display("Time\tA  S  | Y[3] Y[2] Y[1] Y[0]");
        $monitor("%g\t%b  %b |   %b     %b     %b     %b", $time, a, s, y[3], y[2], y[1], y[0]);

        // All input combinations
        a = 0; s = 2'b00; #10; // Expect y = 0000
        a = 0; s = 2'b01; #10; // Expect y = 0000
        a = 0; s = 2'b10; #10; // Expect y = 0000
        a = 0; s = 2'b11; #10; // Expect y = 0000

        a = 1; s = 2'b00; #10; // Expect y = 0001
        a = 1; s = 2'b01; #10; // Expect y = 0010
        a = 1; s = 2'b10; #10; // Expect y = 0100
        a = 1; s = 2'b11; #10; // Expect y = 1000

        $finish;
    end
endmodule

Verilog Basics/Combinational Circuits - Gate Level/Data Selection and Routing Circuits/DEMUX/1x4 DEMUX using 1x2 DEMUX/demux_1x4.vcd
$date
	Sat Jun 14 22:19:12 2025
$end
$version
	Icarus Verilog
$end
$timescale
	1ps
$end
$scope module tb_demux_1x4 $end
$var wire 4 ! y [3:0] $end
$var reg 1 " a $end
$var reg 2 # s [1:0] $end
$scope module DUT $end
$var wire 1 " a $end
$var wire 2 $ s [1:0] $end
$var wire 4 % y [3:0] $end
$var wire 2 & i [1:0] $end
$scope module D1 $end
$var wire 1 " a $end
$var wire 1 ' s $end
$var wire 1 ( sn $end
$var wire 2 ) y [1:0] $end
$upscope $end
$scope module D2 $end
$var wire 1 * a $end
$var wire 1 + s $end
$var wire 1 , sn $end
$var wire 2 - y [1:0] $end
$upscope $end
$scope module D3 $end
$var wire 1 . a $end
$var wire 1 / s $end
$var wire 1 0 sn $end
$var wire 2 1 y [1:0] $end
$upscope $end
$upscope $end
$upscope $end
$enddefinitions $end
$comment Show the parameter values. $end
$dumpall
$end
#0
$dumpvars
b0 1
10
0/
0.
b0 -
1,
0+
0*
b0 )
1(
0'
b0 &
b0 %
b0 $
b0 #
0"
b0 !
$end
#10000
0,
00
1+
1/
b1 #
b1 $
#20000
0(
1,
10
1'
0+
0/
b10 #
b10 $
#30000
0,
00
1+
1/
b11 #
b11 $
#40000
b1 -
1*
b1 !
b1 %
b0 1
1(
1,
10
0.
0'
0+
0/
b1 &
b1 )
b0 #
b0 $
1"
#50000
0,
b10 !
b10 %
b10 -
00
1+
1/
b1 #
b1 $
#60000
0*
b1 1
1.
0(
b10 &
b10 )
1,
b100 !
b100 %
b0 -
10
1'
0+
0/
b10 #
b10 $
#70000
0,
00
b1000 !
b1000 %
b10 1
1+
1/
b11 #
b11 $
