Verilog Basics/Combinational Circuits - Gate Level/Data Selection and Routing Circuits/Decoders/3x8 Decoder/top.v
module dec_3x8 (
    output [7:0] y,
    input [2:0] d
);
    wire d0_n, d1_n, d2_n;
    not N1(d0_n, d[0]);
    not N2(d1_n, d[1]);
    not N3(d2_n, d[2]);

    and G1(y[0], d2_n, d1_n, d0_n);
    and G2(y[1], d2_n, d1_n, d[0]);
    and G3(y[2], d2_n, d[1], d0_n);
    and G4(y[3], d2_n, d[1], d[0]);
    and G5(y[4], d[2], d1_n, d0_n);
    and G6(y[5], d[2], d1_n, d[0]);
    and G7(y[6], d[2], d[1], d0_n);
    and G8(y[7], d[2], d[1], d[0]);

endmodule

Verilog Basics/Combinational Circuits - Gate Level/Data Selection and Routing Circuits/Decoders/3x8 Decoder/tb_dec_3x8.v
`timescale 1ns/1ps

module tb_dec_3x8;

    reg [2:0] d;
    wire [7:0] y;

    dec_3x8 uut(y, d);

    initial begin
        $dumpfile("dec_3x8.vcd");
        $dumpvars(0, tb_dec_3x8);

        $display("Time\tInput d\t|\tOutput y");
        $display("----------------------------------------");

        d = 3'b000; #10;
        $display("%0t\t%3b\t|\t%8b", $time, d, y);

        d = 3'b001; #10;
        $display("%0t\t%3b\t|\t%8b", $time, d, y);

        d = 3'b010; #10;
        $display("%0t\t%3b\t|\t%8b", $time, d, y);

        d = 3'b011; #10;
        $display("%0t\t%3b\t|\t%8b", $time, d, y);

        d = 3'b100; #10;
        $display("%0t\t%3b\t|\t%8b", $time, d, y);

        d = 3'b101; #10;
        $display("%0t\t%3b\t|\t%8b", $time, d, y);

        d = 3'b110; #10;
        $display("%0t\t%3b\t|\t%8b", $time, d, y);

        d = 3'b111; #10;
        $display("%0t\t%3b\t|\t%8b", $time, d, y);

        $finish;
    end

endmodule

Verilog Basics/Combinational Circuits - Gate Level/Data Selection and Routing Circuits/Decoders/3x8 Decoder/dec_3x8.vcd
$date
	Sun Jun 15 15:59:18 2025
$end
$version
	Icarus Verilog
$end
$timescale
	1ps
$end
$scope module tb_dec_3x8 $end
$var wire 8 ! y [7:0] $end
$var reg 3 " d [2:0] $end
$scope module uut $end
$var wire 3 # d [2:0] $end
$var wire 1 $ d0_n $end
$var wire 1 % d1_n $end
$var wire 1 & d2_n $end
$var wire 8 ' y [7:0] $end
$upscope $end
$upscope $end
$enddefinitions $end
$comment Show the parameter values. $end
$dumpall
$end
#0
$dumpvars
b1 '
1&
1%
1$
b0 #
b0 "
b1 !
$end
#10000
0$
b10 !
b10 '
b1 "
b1 #
#20000
1$
0%
b100 !
b100 '
b10 "
b10 #
#30000
0$
b1000 !
b1000 '
b11 "
b11 #
#40000
1$
1%
0&
b10000 !
b10000 '
b100 "
b100 #
#50000
0$
b100000 !
b100000 '
b101 "
b101 #
#60000
1$
0%
b1000000 !
b1000000 '
b110 "
b110 #
#70000
0$
b10000000 !
b10000000 '
b111 "
b111 #
